actupy/__init__.py
actupy-0.0.1.dist-info/METADATA
actupy-0.0.1.dist-info/WHEEL
actupy-0.0.1.dist-info/top_level.txt
actupy-0.0.1.dist-info/RECORD
